README.md
pandoc_imagine.py
setup.cfg
setup.py
pandoc_imagine.egg-info/PKG-INFO
pandoc_imagine.egg-info/SOURCES.txt
pandoc_imagine.egg-info/dependency_links.txt
pandoc_imagine.egg-info/entry_points.txt
pandoc_imagine.egg-info/requires.txt
pandoc_imagine.egg-info/top_level.txt