Metadata-Version: 2.1
Name: pandoc-imagine
Version: 0.1.7
Summary: A filter to process codeblocks into images or ascii art
Home-page: https://github.com/hertogp/imagine
Author: hertogp
Author-email: git.hertogp@gmail.com
License: UNKNOWN
Keywords: pandoc,filter,codeblock,image,ascii-art
Platform: UNKNOWN
Classifier: Development Status :: 3 - Alpha
Classifier: Environment :: Console
Classifier: Intended Audience :: End Users/Desktop
Classifier: Intended Audience :: Developers
Classifier: License :: OSI Approved :: MIT License
Classifier: Operating System :: OS Independent
Classifier: Programming Language :: Python :: 2.7
Classifier: Programming Language :: Python :: 3.5
Classifier: Programming Language :: Python :: 3.6
Classifier: Topic :: Text Processing :: Filters
Classifier: Natural Language :: English
